myanonamouse/__init__.py
myanonamouse-0.1.2.dist-info/METADATA
myanonamouse-0.1.2.dist-info/WHEEL
myanonamouse-0.1.2.dist-info/RECORD
