Metadata-Version: 2.1
Name: myanonamouse
Version: 0.1.2
Summary: Python client for the MyAnonaMouse API
License: MIT
Author: Jasmin Le Roux
Author-email: theblazehen@gmail.com
Requires-Python: >=3.8,<4.0
Classifier: License :: OSI Approved :: MIT License
Classifier: Programming Language :: Python :: 3
Classifier: Programming Language :: Python :: 3.8
Classifier: Programming Language :: Python :: 3.9
Classifier: Programming Language :: Python :: 3.10
Classifier: Programming Language :: Python :: 3.11
Classifier: Programming Language :: Python :: 3.12
Requires-Dist: lxml (>=5.2.2,<6.0.0)
Requires-Dist: requests (>=2.32.3,<3.0.0)
